dbtrunner/__init__.py
dbtrunner/dbt/v1/dbt_pb2.py
dbtrunner/dbt/v1/dbt_pb2_grpc.py
dbtrunner-0.6.1.dist-info/WHEEL
dbtrunner-0.6.1.dist-info/METADATA
dbtrunner-0.6.1.dist-info/RECORD
