Metadata-Version: 2.1
Name: dbtrunner
Version: 0.6.1
Summary: Python client stubs for invoking DBT runner calls
Author: Tom Collingwood
Author-email: tcollingwood@petsathome.co.uk
Requires-Python: >=3.6,<4.0
Classifier: Programming Language :: Python :: 3
Classifier: Programming Language :: Python :: 3.10
Classifier: Programming Language :: Python :: 3.6
Classifier: Programming Language :: Python :: 3.7
Classifier: Programming Language :: Python :: 3.8
Classifier: Programming Language :: Python :: 3.9
Requires-Dist: google_api (>=0.1.12,<0.2.0)
Requires-Dist: grpc-gateway-protoc-gen-openapiv2 (>=0.1.0,<0.2.0)
Requires-Dist: grpcio (>=1.41.0,<2.0.0)
